importd/__init__.py
importd/exceptions.py
importd/urlconf.py
importd-0.4.3.dist-info/DESCRIPTION.rst
importd-0.4.3.dist-info/METADATA
importd-0.4.3.dist-info/metadata.json
importd-0.4.3.dist-info/pbr.json
importd-0.4.3.dist-info/RECORD
importd-0.4.3.dist-info/top_level.txt
importd-0.4.3.dist-info/WHEEL
importd-0.4.3.dist-info/zip-safe
