Metadata-Version: 2.0
Name: importd
Version: 0.4.3
Summary: A django based miniframework, inspired by Sinatra
Home-page: https://github.com/amitu/importd
Author: Amit Upadhyay
Author-email: upadhyay@gmail.com
License: BSD
Keywords: Django,Miniframework,ImportD,Web,Minimalism
Platform: UNKNOWN
Classifier: Development Status :: 5 - Production/Stable
Classifier: Intended Audience :: Developers
Classifier: Intended Audience :: End Users/Desktop
Classifier: Intended Audience :: System Administrators
Classifier: Intended Audience :: Information Technology
Classifier: Intended Audience :: Other Audience
Classifier: Natural Language :: English
Classifier: Operating System :: OS Independent
Classifier: Operating System :: POSIX :: Linux
Classifier: Operating System :: Microsoft :: Windows
Classifier: Operating System :: MacOS :: MacOS X
Classifier: Programming Language :: Python
Classifier: Programming Language :: Python :: 2
Classifier: Programming Language :: Python :: 2.7
Classifier: Programming Language :: Python :: 3
Classifier: Programming Language :: Python :: 3.4
Classifier: Programming Language :: Python :: Implementation :: CPython
Classifier: Topic :: Software Development
Requires-Dist: fhurl (>=0.1.7)
Requires-Dist: smarturls
Requires-Dist: six
Requires-Dist: Django (>=1.3)
Requires-Dist: dj-database-url
Requires-Dist: path.py
Requires-Dist: envdir
Requires-Dist: speaklater
